pkg_pyknnclassifier/__init__.py
pkg_pyknnclassifier/calculate_distance.py
pkg_pyknnclassifier/data_loading.py
pkg_pyknnclassifier/evaluate.py
pkg_pyknnclassifier/find_neighbors.py
pkg_pyknnclassifier/predict.py
pkg_pyknnclassifier/scaling.py
pkg_pyknnclassifier-0.1.0.dist-info/LICENSE
pkg_pyknnclassifier-0.1.0.dist-info/METADATA
pkg_pyknnclassifier-0.1.0.dist-info/WHEEL
pkg_pyknnclassifier-0.1.0.dist-info/RECORD
