Metadata-Version: 2.1
Name: pkg_pyknnclassifier
Version: 0.1.0
Summary: A k-Nearest Neighbors (KNN) classifier for Python.
License: MIT
Author: Bill Wan
Requires-Python: >=3.9,<4.0
Classifier: License :: OSI Approved :: MIT License
Classifier: Programming Language :: Python :: 3
Classifier: Programming Language :: Python :: 3.9
Classifier: Programming Language :: Python :: 3.10
Classifier: Programming Language :: Python :: 3.11
Classifier: Programming Language :: Python :: 3.12
Requires-Dist: numpy (>=1.26.3,<2.0.0)
Requires-Dist: pandas (>=2.1.4,<3.0.0)
Requires-Dist: scikit-learn (>=1.3.2,<2.0.0)
